<?xml version="1.0" encoding="UTF-8" standalone="no" ?>
<multimarker markers="2">
    <marker index="8" status="1">
        <corner x="-2.2" y="-2.2" z="0.0" />
        <corner x="2.2" y="-2.2" z="0.0" />
        <corner x="2.2" y="2.2" z="0.0" />
        <corner x="-2.2" y="2.2" z="0.0" />
    </marker>
    <marker index="9" status="1">
        <corner x="-2.2" y="11.8" z="0.0" />
        <corner x="2.2" y="11.8" z="0.0" />
        <corner x="2.2" y="16.2" z="0.0" />
        <corner x="-2.2" y="16.2" z="0.0" />
    </marker>
</multimarker>
